pyogero/__init__.py
pyogero/asyncio/__init__.py
pyogero/const.py
pyogero/exceptions.py
pyogero/resources/__init__.py
pyogero/resources/ogero.pem
pyogero/types.py
pyogero/utils.py
pyogero-0.10.2.dist-info/LICENSE
pyogero-0.10.2.dist-info/METADATA
pyogero-0.10.2.dist-info/WHEEL
pyogero-0.10.2.dist-info/RECORD
