Metadata-Version: 2.1
Name: pyogero
Version: 0.10.2
Summary: Ogero API module
Home-page: https://github.com/oraad/pyogero
License: MIT
Keywords: ogero,internet,api,lebanon
Author: Omar Raad
Author-email: omarraad@gmail.com
Requires-Python: >=3.12,<4
Classifier: Development Status :: 4 - Beta
Classifier: License :: OSI Approved :: MIT License
Classifier: Operating System :: OS Independent
Classifier: Programming Language :: Python :: 3
Classifier: Programming Language :: Python :: 3.12
Requires-Dist: aiohttp (>=3.10.3)
Requires-Dist: beautifulsoup4 (>=4.12.3)
Requires-Dist: pydantic (>=1.10.17)
Requires-Dist: requests (>=2.32.3)
Project-URL: Issues, https://github.com/oraad/pyogero/issues/
Project-URL: Repository, https://github.com/oraad/pyogero
